<lxs>
    <scene root="demoRoot" axis_length="5"/>

    <views default="defaultCamera">
        <perspective id="defaultCamera" near="0.1" far="500" angle="45">
            <from x="67" y="50" z="30" />
            <to x="0" y="-2" z="0" />
        </perspective>

        <perspective id="Camera1" near="0.1" far="500" angle="90">
            <from x="10" y="5" z="10" />
            <to x="10" y="5" z="0" />
        </perspective>

        <perspective id="Camera2" near="0.1" far="500" angle="90">
            <from x="10" y="5" z="10" />
            <to x="0" y="5" z="10" />
        </perspective>

        <perspective id="Camera3" near="0.1" far="500" angle="90">
            <from x="10" y="5" z="10" />
            <to x="10" y="5" z="20" />
        </perspective>

        <perspective id="Camera4" near="0.1" far="500" angle="90">
            <from x="10" y="5" z="10" />
            <to x="20" y="5" z="10" />
        </perspective>

    </views>

    <globals>
        <ambient r="0.2" g="0.2" b="0.2" a="1.0" />
        <background r="0.8" g="0.8" b="0.8" a="1.0" />
    </globals>

    <lights>
        <omni id="demoLight" enabled="1">
            <location x="5" y="5" z="5" w="1.0" />
            <ambient r="0" g="0" b="0" a="1.0" />
            <diffuse r="1.0" g="1.0" b="1.0" a="1.0" />
            <specular r="1.0" g="1.0" b="1.0" a="1.0" />
            <attenuation constant="1" linear="0" quadratic="0" />
        </omni>
        <omni id="Light1" enabled="1">
            <location x="-1" y="7" z="16" w="1.0" />
            <ambient r="0" g="0" b="0" a="1.0" />
            <diffuse r="1.0" g="1.0" b="1.0" a="1.0" />
            <specular r="1.0" g="1.0" b="1.0" a="1.0" />
            <attenuation constant="0" linear="1" quadratic="0" />
        </omni>
    </lights>

    <textures>
        <texture id="demoTexture" file="scenes/images/vidral.jpg" />
        <texture id="wallTexture" file="scenes/images/darkred.jpg" />
        <texture id="woodTexture" file="scenes/images/wood.jpg" />
        <texture id="doorTexture" file="scenes/images/door.jpg" />
        <texture id="blackTexture" file="scenes/images/black.jpg" />
        <texture id="netflixTexture" file="scenes/images/netflix.jpg" />
        <texture id="floorTexture" file="scenes/images/floor.jpg" />
        <texture id="steelTexture" file="scenes/images/steel.jpg" />
        <texture id="drawerTexture" file="scenes/images/drawer.jpg" />
        <texture id="chairTexture" file="scenes/images/chair.jpg" />
        <texture id="whiteTexture" file="scenes/images/white.jpg" />
        <texture id="paintingTexture" file="scenes/images/painting.jpg" />
        <texture id="landscapeTexture" file="scenes/images/landscape.jpg" />
        <texture id="glassTexture" file="scenes/images/glass.jpg" />
        <texture id="earthTexture" file="scenes/images/earth.jpg" />
        <texture id="vaseTexture" file="scenes/images/vase.jpg" />
        <texture id="cactusTexture" file="scenes/images/cactus.jpg" />
        <texture id="blueTexture" file="scenes/images/blue.jpg" />
        <texture id="redTexture" file="scenes/images/red.jpg" />
        <texture id="greenTexture" file="scenes/images/green.jpg" />
        <texture id="orangeTexture" file="scenes/images/orange.jpg" />
        <texture id="appleTexture" file="scenes/images/apple.jpg" />
        <texture id="greenSofaTexture" file="scenes/images/greensofa.jpg" />
    </textures>

    <materials>
        <material id="demoMaterial" shininess="10">
            <emission r="0.0" g="0.0" b="0.0" a="1.0" />
            <ambient r="1.0" g="1.0" b="1.0" a="1.0" />
            <diffuse r="0.0" g="0.0" b="0.0" a="0.0" />
            <specular r="0.0" g="0.0" b="0.0" a="1.0" />
        </material>

        <material id="moreDiffuse" shininess="10">
            <emission r="0.5" g="0.5" b="0.5" a="1.0" />
            <ambient r="0.7" g="0.7" b="0.7" a="1.0" />
            <diffuse r="1.0" g="1.0" b="1.0" a="1.0" />
            <specular r="0.5" g="0.5" b="0.5" a="1.0" />
        </material>
    </materials>

    <transformations>
        <transformation id="demoTransform">
            <scale x="5" y="1" z="5" />
            <rotate axis="x" angle="-45" />
            <rotate axis="z" angle="-45" />
        </transformation>
    </transformations>

    <animations>
        <animation id="hey" >
            <keyframe instant="5">
                <translate x="10" y="10" z="10" />
                <rotate angle_x="45" angle_y="0" angle_z="0" />
                <scale x="1" y="1" z="1" />
            </keyframe>
        </animation>
    </animations>

    <primitives>
        <primitive id="demoRectangle">
            <rectangle x1="-0.5" y1="-1" x2="0.5" y2="1" />
        </primitive>

        <primitive id="demoTriangle">
            <triangle x1="0" y1="0" z1="0" x2="2" y2="0" z2="0" x3="0" y3="2" z3="0" />
        </primitive>

        <primitive id="demoSphere">
            <sphere radius="1" slices="20" stacks="20" />
        </primitive>

        <primitive id="demoCylinder">
            <cylinder base="2" top="2" height="4" slices="20" stacks="20" />
        </primitive>

        <primitive id="vase">
            <cylinder base="1.5" top="2" height="4" slices="20" stacks="20" />
        </primitive>

        <primitive id="demoTorus">
            <torus slices="20" loops="20" outer="1" inner="1" />
        </primitive>

        <primitive id="demoPlane">
            <plane npartsU="5" npartsV="8" />
        </primitive>

        <primitive id="demoPatch">
            <patch npointsU="1" npointsV="2" npartsU="5" npartsV="8" >
                <controlpoint xx="0" yy="0" zz="0" />
                <controlpoint xx="0" yy="0.5" zz="1" />
                <controlpoint xx="0" yy="1" zz="0" />
                <controlpoint xx="1" yy="0" zz="0" />
                <controlpoint xx="1" yy="0.5" zz="1" />
                <controlpoint xx="1" yy="1" zz="0" />
                
            </patch>
        </primitive> 
    </primitives>

    <components>
        <component id="demoRoot">
            <transformation>
            </transformation>
            <materials>
                <material id="demoMaterial" />
            </materials>
            <texture id="demoTexture" length_s="1" length_t="1"/>
            <children>
                <componentref id="Walls" />
                <componentref id="Door" />
                <componentref id="TV" />
                <componentref id="TVcabinet" />
                <componentref id="Floor" />
                <componentref id="Table" />
                <componentref id="Chairs" />
                <componentref id="Painting" />
                <componentref id="Window" />
                <componentref id="Cabinet" />
                <componentref id="Plant" />
                <componentref id="Basket" />
                <componentref id="Fruit" />
                <componentref id="Sofa" />

 
            </children>
        </component>

        <component id="Walls">
            <transformation>
            </transformation>
            <materials>
                <material id="moreDiffuse" />
                <material id="demoMaterial" />
            </materials>
            <texture id="demoTexture" length_s="1" length_t="1"/>
            <children>
                <componentref id="Wall1" />
                <componentref id="Footer1" />
                <componentref id="Wall2" />
                <componentref id="Footer2" />
                <componentref id="Wall3" />
                <componentref id="Footer3" />
                <componentref id="Wall4" />
                <componentref id="doorFooter1" />
                <componentref id="doorFooter2" />
            </children>
        </component>

        <component id="Wall1">
            <transformation>
                <translate x="10" y="5" z="0" />
                <scale x="20" y="5" z="1" />
            </transformation>
            <materials>
                <material id="inherit" />
            </materials>
            <texture id="wallTexture" length_s="1" length_t="1"/>
            <children>
                <primitiveref id="demoRectangle"/>
            </children>
        </component>

        <component id="Wall2">
            <transformation>
                <translate x="10" y="5" z="0" />
                <scale x="20" y="5" z="1" />
                <rotate axis="x" angle="180" />
                <translate x="0" y="0" z="-20" />
            </transformation>
            <materials>
                <material id="inherit" />
            </materials>
            <texture id="wallTexture" length_s="1" length_t="1"/>
            <children>
                <primitiveref id="demoRectangle"/>
            </children>
        </component>

        <component id="Wall3">
            <transformation>
                <translate x="0" y="5" z="10" /> 
                <rotate axis="y" angle="90" />
                <scale x="20" y="5" z="1" />
            </transformation>
            <materials>
                <material id="inherit" />
            </materials>
            <texture id="wallTexture" length_s="1" length_t="1"/>
            <children>
                <primitiveref id="demoRectangle"/>
            </children> 
        </component> 

        <component id="Wall4">
            <transformation>
                <translate x="20" y="5" z="10" />
                <rotate axis="y" angle="-90" />
                <scale x="20" y="5" z="1" />
            </transformation>
            <materials>
                <material id="inherit" />
            </materials>
            <texture id="wallTexture" length_s="1" length_t="1"/>
            <children>
                <primitiveref id="demoRectangle"/>
            </children>
        </component>

        <!-- Cube -->
        <component id="Cube">
            <transformation>
            </transformation>
            <materials>
                <material id="inherit" />
            </materials>
            <texture id="inherit" length_s="1" length_t="1"/>
            <children>
                <componentref id="cubePart1" />
                <componentref id="cubePart2" />
                <componentref id="cubePart3" />
                <componentref id="cubePart4" />
                <componentref id="cubePart5" />
                <componentref id="cubePart6" />
            </children>
        </component>

        <component id="cubePart1">
            <transformation>
                <translate x="0.5" y="0.5" z="1" />
                <scale x="1" y="0.5" z="1" />
            </transformation>
            <materials>
                <material id="inherit" />
            </materials>
            <texture id="inherit" length_s="1" length_t="1"/>
            <children>
                <primitiveref id="demoRectangle"/>
            </children>
        </component>

        <component id="cubePart2">
            <transformation>
                <translate x="0" y="1" z="0" />
                <rotate axis="x" angle="180" />
                <translate x="0.5" y="0.5" z="0" />
                <scale x="1" y="0.5" z="1" />
            </transformation>
            <materials>
                <material id="inherit" />
            </materials>
            <texture id="inherit" length_s="1" length_t="1"/>
            <children>
                <primitiveref id="demoRectangle"/>
            </children>
        </component>

        <component id="cubePart3">
            <transformation>
                <rotate axis="y" angle="-90" />
                <translate x="0.5" y="0.5" z="0" />
                <scale x="1" y="0.5" z="1" />
            </transformation>
            <materials>
                <material id="inherit" />
            </materials>
            <texture id="inherit" length_s="1" length_t="1"/>
            <children>
                <primitiveref id="demoRectangle"/>
            </children>
        </component>

        <component id="cubePart4">
            <transformation>
                <translate x="1" y="0" z="1" />
                <rotate axis="y" angle="90" />
                <translate x="0.5" y="0.5" z="0" />
                <scale x="1" y="0.5" z="1" />
            </transformation>
            <materials>
                <material id="inherit" />
            </materials>
            <texture id="inherit" length_s="1" length_t="1"/>
            <children>
                <primitiveref id="demoRectangle"/>
            </children>
        </component>

        <component id="cubePart5">
            <transformation>
                <translate x="0" y="0" z="0" />
                <rotate axis="x" angle="90" />
                <translate x="0.5" y="0.5" z="0" />
                <scale x="1" y="0.5" z="1" />
            </transformation>
            <materials>
                <material id="inherit" />
            </materials>
            <texture id="inherit" length_s="1" length_t="1"/>
            <children>
                <primitiveref id="demoRectangle"/>
            </children>
        </component>

        <component id="cubePart6">
            <transformation>
                <translate x="0" y="1" z="1" />
                <rotate axis="x" angle="-90" />
                <translate x="0.5" y="0.5" z="0" />
                <scale x="1" y="0.5" z="1" />
            </transformation>
            <materials>
                <material id="inherit" />
            </materials>
            <texture id="inherit" length_s="1" length_t="1"/>
            <children>
                <primitiveref id="demoRectangle"/>
            </children>
        </component>

        <!-- Footers -->
        <component id="Footer1">
            <transformation>
                <scale x="20" y="0.5" z="0.1" />
            </transformation>
            <materials>
                <material id="inherit" />
            </materials>
            <texture id="woodTexture" length_s="1" length_t="1"/>
            <children>
                <componentref id="Cube" />
            </children>
        </component>

        <component id="Footer2">
            <transformation>
                <scale x="0.1" y="0.5" z="20" />
            </transformation>
            <materials>
                <material id="inherit" />
            </materials>
            <texture id="woodTexture" length_s="1" length_t="1"/>
            <children>
                <componentref id="Cube" />
            </children>
        </component>

        <component id="Footer3">
            <transformation>
                <translate x="0" y="0" z="19.9" />
                <scale x="20" y="0.5" z="0.1" />
            </transformation>
            <materials>
                <material id="inherit" />
            </materials>
            <texture id="woodTexture" length_s="1" length_t="1"/>
            <children>
                <componentref id="Cube" />
            </children>
        </component>

        <component id="doorFooter1">
            <transformation>
                <translate x="19.9" y="0" z="0" />
                <scale x="0.1" y="0.5" z="13.4" /> 
            </transformation>
            <materials>
                <material id="inherit" />
            </materials>
            <texture id="woodTexture" length_s="1" length_t="1"/>
            <children>
                <componentref id="Cube" />
            </children>
        </component> 

        <component id="doorFooter2">
            <transformation>
                <translate x="19.9" y="0" z="16.6" />
                <scale x="0.1" y="0.5" z="3.4" /> 
            </transformation>
            <materials>
                <material id="inherit" />
            </materials>
            <texture id="woodTexture" length_s="1" length_t="1"/>
            <children>
                <componentref id="Cube" />
            </children>
        </component> 

        <!-- Door -->
        <component id="Door">
            <transformation>
                <translate x="19.4" y="0" z="15" />
                <scale x="1" y="4" z="3.2" /> 
                <translate x="0.5" y="1" z="0" />
                <rotate axis="y" angle="-90"/>
            </transformation>
            <materials>
                <material id="moreDiffuse" />
            </materials>
            <texture id="doorTexture" length_s="1" length_t="2"/>
            <children>
                <primitiveref id="demoRectangle" />
            </children>
        </component>

        <!-- TV -->
        <component id="TV">
            <transformation>
                <translate x="4.5" y="0.85" z="1" />
            </transformation>
            <materials>
                <material id="moreDiffuse" />
            </materials>
            <texture id="blackTexture" length_s="1" length_t="1"/>
            <children>
                <componentref id="TVbase" />
                <componentref id="TVsuport"/>
                <componentref id="smallcube" />
                <componentref id="bigcube" />
                <componentref id="TVfooter1"/>
                <componentref id="TVfooter2"/>
                <componentref id="TVfooter3"/>
                <componentref id="TVfooter4"/>
                <componentref id="TVscreen"/>
            </children>
        </component>

        <component id="TVbase">
            <transformation>              
                <translate x="0" y="1.35" z="0" />
                <scale x="1.5" y="0.1" z="0.8" />
            </transformation>
            <materials>
                <material id="inherit" />
            </materials>
            <texture id="inherit" length_s="1" length_t="1"/>
            <children>
                <componentref id="Cube" />
            </children>
        </component>

        <component id="TVsuport">
            <transformation>
                <translate x="0.75" y="2.8" z="0.35" />
                <scale x="0.1" y="0.35" z="0.1" />
                <rotate axis="x" angle="90" />
            </transformation>
            <materials>
                <material id="inherit" />
            </materials>
            <texture id="inherit" length_s="1" length_t="1"/>
            <children>
                <primitiveref id="demoCylinder" />
            </children>
        </component>


        <component id="smallcube">
            <transformation>
                <translate x="0.4" y="2.7" z="0.15"/>
                <scale x="0.7" y="0.7" z="0.7" />
            </transformation>
            <materials>
                <material id="inherit" />
            </materials>
            <texture id="inherit" length_s="1" length_t="1"/>
            <children>
                <componentref id="Cube" />
            </children>
        </component>

        <component id="bigcube">
            <transformation>
                <translate x="-1" y="2" z="0.65"/>
                <scale x="3.5" y="2.8" z="0.2" />
            </transformation>
            <materials>
                <material id="inherit" />
            </materials>
            <texture id="inherit" length_s="1" length_t="1"/>
            <children>
                <componentref id="Cube" />
            </children>
        </component>

        <component id="TVfooter1">
            <transformation>
                <translate x="-1.5" y="1.8" z="0.65"/>
                <scale x="0.5" y="3.2" z="0.4" />
            </transformation>
            <materials>
                <material id="inherit" />
            </materials>
            <texture id="inherit" length_s="1" length_t="1"/>
            <children>
                <componentref id="Cube" />
            </children>
        </component>

        <component id="TVfooter2">
            <transformation>
                <translate x="2.5" y="1.8" z="0.65"/>
                <scale x="0.5" y="3.2" z="0.4" />
            </transformation>
            <materials>
                <material id="inherit" />
            </materials>
            <texture id="inherit" length_s="1" length_t="1"/>
            <children>
                <componentref id="Cube" />
            </children>
        </component>

        <component id="TVfooter3">
            <transformation>
                <translate x="-1" y="4.8" z="0.65" />
                <scale x="3.5" y="0.2" z="0.4" />
            </transformation>
            <materials>
                <material id="inherit" />
            </materials>
            <texture id="inherit" length_s="1" length_t="1"/>
            <children>
                <componentref id="Cube" />
            </children>
        </component>

        <component id="TVfooter4">
            <transformation>
                <translate x="-1" y="1.8" z="0.65" />
                <scale x="3.5" y="0.2" z="0.4" />
            </transformation>
            <materials>
                <material id="inherit" />
            </materials>
            <texture id="inherit" length_s="1" length_t="2"/>
            <children>
                <componentref id="Cube" />
            </children>
        </component>

        <component id="TVscreen">
            <transformation>    
                <translate x="0.75" y="3.4" z="1" />
                <scale x="3.5" y="1.5" z="1" />
            </transformation>
            <materials>
                <material id="inherit" />
            </materials>
            <texture id="netflixTexture" length_s="1" length_t="2"/>
            <children>
                <primitiveref id="demoRectangle" />
            </children>
        </component>

        <!-- Floor -->
        <component id="Floor">
            <transformation>   
                <translate x="10" y="0" z="10" />
                <scale x="20" y="1" z="10" />
                <rotate axis="x" angle="-90"/>
            </transformation>
            <materials>
                <material id="moreDiffuse" />
            </materials>
            <texture id="floorTexture" length_s="1" length_t="0.5"/>
            <children>
                <primitiveref id="demoRectangle" />
            </children>
        </component> 


        <!-- TV Cabinet -->
        <component id="TVcabinet">
            <transformation>

            </transformation>
            <materials>
                <material id="moreDiffuse" />
            </materials>
            <texture id="woodTexture" length_s="1" length_t="1"/>
            <children>
                <componentref id="TVcabinet_body" />
                <componentref id="TVcabinet_legs" />
                <componentref id="TVdrawers" />
            </children>
        </component>

        <component id="TVcabinet_body">
            <transformation>
                <translate x="1" y="0.7" z="0.3" />
                <scale x="8" y="1.5" z="3" />
            </transformation>
            <materials>
                <material id="inherit" />
            </materials>
            <texture id="inherit" length_s="1" length_t="1"/>
            <children>
                <componentref id="Cube" />
            </children>
        </component> 

        <component id="TVcabinet_legs">
            <transformation>
            </transformation>
            <materials>
                <material id="inherit" />
            </materials>
            <texture id="steelTexture" length_s="1" length_t="1"/>
            <children>
                <componentref id="TVcabinet_leg1" />
                <componentref id="TVcabinet_leg2" />
                <componentref id="TVcabinet_leg3" />
                <componentref id="TVcabinet_leg4" />
            </children>
        </component>

        <component id="TVcabinet_leg1">
            <transformation>
                <translate x="1.7" y="0.8" z="3" />
                <scale  x="0.1" y="0.2" z="0.1" />
                <rotate axis="x" angle="90" />
            </transformation>
            <materials>
                <material id="inherit" />
            </materials>
            <texture id="inherit" length_s="1" length_t="1"/>
            <children>
                <primitiveref id="demoCylinder" />
            </children>
        </component> 

        <component id="TVcabinet_leg2">
            <transformation>
                <translate x="8.3" y="0.8" z="3" />
                <scale  x="0.1" y="0.2" z="0.1" />
                <rotate axis="x" angle="90" />
            </transformation>
            <materials>
                <material id="inherit" />
            </materials>
            <texture id="inherit" length_s="1" length_t="1"/>
            <children>
                <primitiveref id="demoCylinder" />
            </children>
        </component> 

        <component id="TVcabinet_leg3">
            <transformation>
                <translate x="8.3" y="0.8" z="0.6" />
                <scale  x="0.1" y="0.2" z="0.1" />
                <rotate axis="x" angle="90" />
            </transformation>
            <materials>
                <material id="inherit" />
            </materials>
            <texture id="inherit" length_s="1" length_t="1"/>
            <children>
                <primitiveref id="demoCylinder" />
            </children>
        </component> 

        <component id="TVcabinet_leg4">
            <transformation>
                <translate x="1.7" y="0.8" z="0.6" />
                <scale  x="0.1" y="0.2" z="0.1" />
                <rotate axis="x" angle="90" />
            </transformation>
            <materials>
                <material id="inherit" />
            </materials>
            <texture id="inherit" length_s="1" length_t="1"/>
            <children>
                <primitiveref id="demoCylinder" />
            </children>
        </component> 

        <component id="TVdrawers">
            <transformation>
            </transformation>
            <materials>
                <material id="inherit" />
            </materials>
            <texture id="inherit" length_s="1" length_t="1"/>
            <children>
                <componentref id="TVdrawer1" />
                <componentref id="TVdrawer2" />
            </children>
        </component> 

        <component id="TVdrawer1">
            <transformation>
                <translate x="1.3" y="0.8" z="3" />
                <scale x="3.7" y="1.3" z="0.5" />
            </transformation>
            <materials>
                <material id="inherit" />
            </materials>
            <texture id="inherit" length_s="1" length_t="1"/>
            <children>
                <componentref id="Cube" />
                <componentref id="Drawer1" />
            </children>
        </component> 

        <component id="TVdrawer2">
            <transformation>
                <translate x="5.1" y="0.8" z="3" />
                <scale x="3.7" y="1.3" z="0.5" />
            </transformation>
            <materials>
                <material id="inherit" />
            </materials>
            <texture id="inherit" length_s="1" length_t="1"/>
            <children>
                <componentref id="Cube" />
                <componentref id="Drawer2" />
            </children>
        </component> 

        <component id="Drawer1">
            <transformation>
                <translate x="0.5" y="0.5" z="1.1" />
                <scale x="1" y="0.5" z="0.4" />
            </transformation>
            <materials>
                <material id="inherit" />
            </materials>
            <texture id="drawerTexture" length_s="1" length_t="2"/>
            <children>
                <primitiveref id="demoRectangle" />
            </children>
        </component> 

        <component id="Drawer2">
            <transformation>
                <translate x="0.5" y="0.5" z="1.1" />
                <scale x="1" y="0.5" z="0.4" />
            </transformation>
            <materials>
                <material id="inherit" />
            </materials>
            <texture id="drawerTexture" length_s="1" length_t="2"/>
            <children>
                <primitiveref id="demoRectangle" />
            </children>
        </component> 


        <!-- Table -->
        <component id="Table">
            <transformation>
            </transformation>
            <materials>
                <material id="moreDiffuse" />
            </materials>
            <texture id="woodTexture" length_s="1" length_t="2"/>
            <children>
                <componentref id="Tabletop" />
                <componentref id="Tablelegs" />
            </children>
        </component> 

        <component id="Tabletop">
            <transformation>
                <translate x="13" y="3" z="3" />
                <scale x="4" y="0.5" z="7" />
            </transformation>
            <materials>
                <material id="inherit" />
            </materials>
            <texture id="inherit" length_s="1" length_t="2"/>
            <children>
                <componentref id="Cube" />
            </children>
        </component> 

        <component id="Tablelegs">
            <transformation>

            </transformation>
            <materials>
                <material id="inherit" />
            </materials>
            <texture id="inherit" length_s="1" length_t="2"/>
            <children>
                <componentref id="Tableleg1" />
                <componentref id="Tableleg2" />
                <componentref id="Tableleg3" />
                <componentref id="Tableleg4" />
            </children>
        </component> 

        <component id="Tableleg1">
            <transformation>
                <translate x="13" y="0" z="3" />
                <scale x="0.5" y="3" z="0.5" />
            </transformation>
            <materials>
                <material id="inherit" />
            </materials>
            <texture id="inherit" length_s="1" length_t="2"/>
            <children>
                <componentref id="Cube" />
            </children>
        </component> 

        <component id="Tableleg2">
            <transformation>
                <translate x="16.5" y="0" z="3" />
                <scale x="0.5" y="3" z="0.5" />
            </transformation>
            <materials>
                <material id="inherit" />
            </materials>
            <texture id="inherit" length_s="1" length_t="2"/>
            <children>
                <componentref id="Cube" />
            </children>
        </component>

        <component id="Tableleg3">
            <transformation>
                <translate x="16.5" y="0" z="9.5" />
                <scale x="0.5" y="3" z="0.5" />
            </transformation>
            <materials>
                <material id="inherit" />
            </materials>
            <texture id="inherit" length_s="1" length_t="2"/>
            <children>
                <componentref id="Cube" />
            </children>
        </component>  

        <component id="Tableleg4">
            <transformation>
                <translate x="13" y="0" z="9.5" />
                <scale x="0.5" y="3" z="0.5" />
            </transformation>
            <materials>
                <material id="inherit" />
            </materials>
            <texture id="inherit" length_s="1" length_t="2"/>
            <children>
                <componentref id="Cube" />
            </children>
        </component>  

        <!-- Chairs -->
        <component id="Chairs">
            <transformation>
            </transformation>
            <materials>
                <material id="moreDiffuse" />
            </materials>
            <texture id="chairTexture" length_s="1" length_t="2"/>
            <children>
                <componentref id="Chair1" />
                <componentref id="Chair2" />
                <componentref id="Chair3" />
                <componentref id="Chair4" />
            </children>
        </component> 

        <component id="Chair1">
            <transformation>
                <translate x="12" y="0" z="4" />
            </transformation>
            <materials>
                <material id="inherit" />
            </materials>
            <texture id="inherit" length_s="1" length_t="2"/>
            <children>
                <componentref id="Chair_leg1" />
                <componentref id="Chair_leg2" />
                <componentref id="Chair_leg3" />
                <componentref id="Chair_leg4" />
                <componentref id="Chair_base" />
                <componentref id="Chair_topleft" />
                <componentref id="Chair_topright" />
                <componentref id="Chair_topmid1" />
                <componentref id="Chair_topmid2" />
            </children>
        </component> 

        <component id="Chair2">
            <transformation>
                <translate x="12" y="0" z="7" />
            </transformation>
            <materials>
                <material id="inherit" />
            </materials>
            <texture id="inherit" length_s="1" length_t="2"/>
            <children>
                <componentref id="Chair_leg1" />
                <componentref id="Chair_leg2" />
                <componentref id="Chair_leg3" />
                <componentref id="Chair_leg4" />
                <componentref id="Chair_base" />
                <componentref id="Chair_topleft" />
                <componentref id="Chair_topright" />
                <componentref id="Chair_topmid1" />
                <componentref id="Chair_topmid2" />
            </children>
        </component> 

        <component id="Chair3">
            <transformation>
                <translate x="18" y="0" z="9" />
                <rotate axis="y" angle="180" />
            </transformation>
            <materials>
                <material id="inherit" />
            </materials>
            <texture id="inherit" length_s="1" length_t="2"/>
            <children>
                <componentref id="Chair_leg1" />
                <componentref id="Chair_leg2" />
                <componentref id="Chair_leg3" />
                <componentref id="Chair_leg4" />
                <componentref id="Chair_base" />
                <componentref id="Chair_topleft" />
                <componentref id="Chair_topright" />
                <componentref id="Chair_topmid1" />
                <componentref id="Chair_topmid2" />
            </children>
        </component> 

        <component id="Chair4">
            <transformation>
                <translate x="18" y="0" z="6" />
                <rotate axis="y" angle="180" />
            </transformation>
            <materials>
                <material id="inherit" />
            </materials>
            <texture id="inherit" length_s="1" length_t="2"/>
            <children>
                <componentref id="Chair_leg1" />
                <componentref id="Chair_leg2" />
                <componentref id="Chair_leg3" />
                <componentref id="Chair_leg4" />
                <componentref id="Chair_base" />
                <componentref id="Chair_topleft" />
                <componentref id="Chair_topright" />
                <componentref id="Chair_topmid1" />
                <componentref id="Chair_topmid2" />
            </children>
        </component> 

        <component id="Chair_leg1">
            <transformation>
                <scale x="0.3" y="2" z="0.3" />
            </transformation>
            <materials>
                <material id="inherit" />
            </materials>
            <texture id="inherit" length_s="1" length_t="2"/>
            <children>
                <componentref id="Cube" />
            </children>
        </component> 

        <component id="Chair_leg2">
            <transformation>
                <translate x="1.7" y="0" z="0" />
                <scale x="0.3" y="2" z="0.3" />
            </transformation>
            <materials>
                <material id="inherit" />
            </materials>
            <texture id="inherit" length_s="1" length_t="2"/>
            <children>
                <componentref id="Cube" />
            </children>
        </component> 

        <component id="Chair_leg3">
            <transformation>
                <translate x="1.7" y="0" z="1.7" />
                <scale x="0.3" y="2" z="0.3" />
            </transformation>
            <materials>
                <material id="inherit" />
            </materials>
            <texture id="inherit" length_s="1" length_t="2"/>
            <children>
                <componentref id="Cube" />
            </children>
        </component> 

        <component id="Chair_leg4">
            <transformation>
                <translate x="0" y="0" z="1.7" />
                <scale x="0.3" y="2" z="0.3" />
            </transformation>
            <materials>
                <material id="inherit" />
            </materials>
            <texture id="inherit" length_s="1" length_t="2"/>
            <children>
                <componentref id="Cube" />
            </children>
        </component> 

        <component id="Chair_base">
            <transformation>
                <translate x="0" y="2" z="0" />
                <scale x="2" y="0.5" z="2" />
            </transformation>
            <materials>
                <material id="inherit" />
            </materials>
            <texture id="inherit" length_s="1" length_t="2"/>
            <children>
                <componentref id="Cube" />
            </children>
        </component> 

        <component id="Chair_topleft">
            <transformation>
                <translate x="0" y="2.5" z="0" />
                <scale x="0.2" y="2.5" z="0.2" />
            </transformation>
            <materials>
                <material id="inherit" />
            </materials>
            <texture id="inherit" length_s="1" length_t="2"/>
            <children>
                <componentref id="Cube" />
            </children>
        </component> 

        <component id="Chair_topright">
            <transformation>
                <translate x="0" y="2.5" z="1.8" />
                <scale x="0.2" y="2.5" z="0.2" />
            </transformation>
            <materials>
                <material id="inherit" />
            </materials>
            <texture id="inherit" length_s="1" length_t="2"/>
            <children>
                <componentref id="Cube" />
            </children>
        </component> 

        <component id="Chair_topmid1">
            <transformation>
                <translate x="0" y="5" z="0" />
                <scale x="0.2" y="0.2" z="2" />
            </transformation>
            <materials>
                <material id="inherit" />
            </materials>
            <texture id="inherit" length_s="1" length_t="2"/>
            <children>
                <componentref id="Cube" />
            </children>
        </component> 

        <component id="Chair_topmid2">
            <transformation>
                <translate x="0" y="4.5" z="0" />
                <scale x="0.2" y="0.2" z="2" />
            </transformation>
            <materials>
                <material id="inherit" />
            </materials>
            <texture id="inherit" length_s="1" length_t="2"/>
            <children>
                <componentref id="Cube" />
            </children>
        </component>  

        <!-- Painting -->
        <component id="Painting">
            <transformation>
            </transformation>
            <materials>
                <material id="moreDiffuse" />
            </materials>
            <texture id="inherit" length_s="1" length_t="2"/>
            <children>
                <componentref id="Painting_Footer1" />
                <componentref id="Painting_Footer2" />
                <componentref id="Painting_Footer3" />
                <componentref id="Painting_Footer4" />
                <componentref id="Drawing" />
            </children>
        </component> 

        <component id="Painting_Footer1">
            <transformation>
                <translate x="19.8" y="5" z="4" />
                <scale x="0.1" y="3" z="0.3" />
            </transformation>
            <materials>
                <material id="inherit" />
            </materials>
            <texture id="whiteTexture" length_s="1" length_t="2"/>
            <children>
                <componentref id="Cube" />
            </children>
        </component> 

        <component id="Painting_Footer2">
            <transformation>
                <translate x="19.8" y="5" z="8" />
                <scale x="0.1" y="3" z="0.3" />
            </transformation>
            <materials>
                <material id="inherit" />
            </materials>
            <texture id="whiteTexture" length_s="1" length_t="2"/>
            <children>
                <componentref id="Cube" />
            </children>
        </component> 

        <component id="Painting_Footer3">
            <transformation>
                <translate x="19.8" y="5" z="4" />
                <scale x="0.1" y="0.3" z="4" />
            </transformation>
            <materials>
                <material id="inherit" />
            </materials>
            <texture id="whiteTexture" length_s="1" length_t="2"/>
            <children>
                <componentref id="Cube" />
            </children>
        </component> 

        <component id="Painting_Footer4">
            <transformation>
                <translate x="19.8" y="8" z="4" />
                <scale x="0.1" y="0.3" z="4.3" />
            </transformation>
            <materials>
                <material id="inherit" />
            </materials>
            <texture id="whiteTexture" length_s="1" length_t="2"/>
            <children>
                <componentref id="Cube" />
            </children>
        </component>

        <component id="Drawing">
            <transformation>
                <translate x="19.8" y="6.6" z="6.15" />
                <rotate axis="y" angle="-90" />
                <scale x="3.75" y="1.4" z="1" />
            </transformation>
            <materials>
                <material id="moreDiffuse" />
            </materials>
            <texture id="paintingTexture" length_s="1" length_t="2"/>
            <children>
                <primitiveref id="demoRectangle" />
            </children>
        </component>

        <!-- Window-->
        <component id="Window">
            <transformation>
            </transformation>
            <materials>
                <material id="moreDiffuse" />
            </materials>
            <texture id="inherit" length_s="1" length_t="2"/>
            <children>
                <componentref id="Landscape" />
                <componentref id="Windowfooter1" />
                <componentref id="Windowfooter2" />
                <componentref id="Windowfooter3" />
                <componentref id="Windowfooter4" />
            </children>
        </component>

        <component id="Landscape">
            <transformation>
                <translate x="0.1" y="5" z="14" />
                <scale x="1" y="2.3" z="6" /> 
                <rotate axis="y" angle="90" />
            </transformation>
            <materials>
                <material id="moreDiffuse" />
            </materials>
            <texture id="landscapeTexture" length_s="1" length_t="2"/>
            <children>
                <primitiveref id="demoRectangle" />
            </children>
        </component>

        <component id="Windowfooter1">
            <transformation>
                <translate x="0" y="2.3" z="10.7" />
                <scale x="0.1" y="5.25" z="0.3" />
            </transformation>
            <materials>
                <material id="inherit" />
            </materials>
            <texture id="whiteTexture" length_s="1" length_t="2"/>
            <children>
                <componentref id="Cube" />
            </children>
        </component> 

        <component id="Windowfooter2">
            <transformation>
                <translate x="0" y="2.3" z="17" />
                <scale x="0.1" y="5.25" z="0.3" />
            </transformation>
            <materials>
                <material id="inherit" />
            </materials>
            <texture id="whiteTexture" length_s="1" length_t="2"/>
            <children>
                <componentref id="Cube" />
            </children>
        </component> 

        <component id="Windowfooter3">
            <transformation>
                <translate x="0" y="2.7" z="11" />
                <rotate axis="x" angle="90" />
                <scale x="0.1" y="6" z="0.4" />
            </transformation>
            <materials>
                <material id="inherit" />
            </materials>
            <texture id="whiteTexture" length_s="1" length_t="2"/>
            <children>
                <componentref id="Cube" />
            </children>
        </component> 

        <component id="Windowfooter4">
            <transformation>
                <translate x="0" y="7.55" z="11" />
                <rotate axis="x" angle="90" />
                <scale x="0.1" y="6" z="0.4" />
            </transformation>
            <materials>
                <material id="inherit" />
            </materials>
            <texture id="whiteTexture" length_s="1" length_t="2"/>
            <children>
                <componentref id="Cube" />
            </children>
        </component> 

        <component id="Cabinet">
            <transformation>
            </transformation>
            <materials>
                <material id="moreDiffuse" />
            </materials>
            <texture id="inherit" length_s="1" length_t="2"/>
            <children>
                <componentref id="Blocks" />
            </children>
        </component> 

        
        <component id="Blocks">
            <transformation>
            </transformation>
            <materials>
                <material id="inherit" />
            </materials>
            <texture id="woodTexture" length_s="1" length_t="2"/>
            <children>
                <componentref id="Block1" />
                <componentref id="Block2" />
                <componentref id="Block3" />
                <componentref id="Block4" />
                <componentref id="Book1" />
                <componentref id="Book2" />
                <componentref id="Book3" />
                <componentref id="Book4" />
            </children>
        </component> 

        <component id="Block1">
            <transformation>
                <translate x="3" y="0" z="18.2" />
                <scale x="0.8" y="0.8" z="0.8" />
            </transformation>
            <materials>
                <material id="inherit" />
            </materials>
            <texture id="inherit" length_s="1" length_t="2"/>
            <children>
                <componentref id="Block" />
            </children>
        </component> 

        <component id="Block2">
            <transformation>
                <translate x="5.65" y="0" z="18.2" />
                <scale x="0.8" y="0.8" z="0.8" />
            </transformation>
            <materials>
                <material id="inherit" />
            </materials>
            <texture id="inherit" length_s="1" length_t="2"/>
            <children>
                <componentref id="Block" />
            </children>
        </component> 

        <component id="Block3">
            <transformation>
                <translate x="5.65" y="2.65" z="18.2" />
                <scale x="0.8" y="0.8" z="0.8" />
            </transformation>
            <materials>
                <material id="inherit" />
            </materials>
            <texture id="inherit" length_s="1" length_t="2"/>
            <children>
                <componentref id="Block" />
            </children>
        </component> 

        <component id="Block4">
            <transformation>
                <translate x="8.30" y="2.65" z="18.2" />
                <scale x="0.8" y="0.8" z="0.8" />
            </transformation>
            <materials>
                <material id="inherit" />
            </materials>
            <texture id="inherit" length_s="1" length_t="2"/>
            <children>
                <componentref id="Block" />
            </children>
        </component> 

        <component id="Block">
            <transformation>
            </transformation>
            <materials>
                <material id="inherit" />
            </materials>
            <texture id="inherit" length_s="1" length_t="2"/>
            <children>
                <componentref id="Cubeleft" />
                <componentref id="Cubetop" />
                <componentref id="Cuberight" />
                <componentref id="Cubebot" />
            </children>
        </component>

        <component id="Cubetop">
            <transformation>
                <scale x="3" y="0.3" z="2" />
            </transformation>
            <materials>
                <material id="inherit" />
            </materials>
            <texture id="inherit" length_s="1" length_t="2"/>
            <children>
                <componentref id="Cube" />
            </children>
        </component>

        <component id="Cubeleft">
            <transformation>
                <scale x="0.3" y="3" z="2" />
            </transformation>
            <materials>
                <material id="inherit" />
            </materials>
            <texture id="inherit" length_s="1" length_t="2"/>
            <children>
                <componentref id="Cube" />
            </children>
        </component>

        <component id="Cuberight">
            <transformation>
                <translate x="3" y="0" z="0" />
                <scale x="0.3" y="3" z="2" />
            </transformation>
            <materials>
                <material id="inherit" />
            </materials>
            <texture id="inherit" length_s="1" length_t="2"/>
            <children>
                <componentref id="Cube" />
            </children>
        </component>

        
        <component id="Cubebot">
            <transformation>
                <translate x="0" y="3" z="0" />
                <scale x="3.3" y="0.3" z="2" />
            </transformation>
            <materials>
                <material id="inherit" />
            </materials>
            <texture id="inherit" length_s="1" length_t="2"/>
            <children>
                <componentref id="Cube" />
            </children>
        </component>

        <component id="Book1">
            <transformation>
                <translate x="3.2" y="0.3" z="18.5" />
            </transformation>
            <materials>
                <material id="inherit" />
            </materials>
            <texture id="blueTexture" length_s="1" length_t="1"/>
            <children>
                <componentref id="Book" />
            </children>
        </component> 

        <component id="Book2">
            <transformation>
                <translate x="3.5" y="0.3" z="18.5" />
            </transformation>
            <materials>
                <material id="inherit" />
            </materials>
            <texture id="redTexture" length_s="1" length_t="1"/>
            <children>
                <componentref id="Book" />
            </children>
        </component> 

        <component id="Book3">
            <transformation>
                <translate x="6" y="0.3" z="18.5" />
            </transformation>
            <materials>
                <material id="inherit" />
            </materials>
            <texture id="redTexture" length_s="1" length_t="1"/>
            <children>
                <componentref id="Book" />
            </children>
        </component> 

        <component id="Book4">
            <transformation>
                <translate x="6.3" y="0.3" z="18.5" />
            </transformation>
            <materials>
                <material id="inherit" />
            </materials>
            <texture id="greenTexture" length_s="1" length_t="1"/>
            <children>
                <componentref id="Book" />
            </children>
        </component> 

        <component id="Book">
            <transformation>
                <scale x="0.3" y="0.8" z="0.6" />
            </transformation>
            <materials>
                <material id="inherit" />
            </materials>
            <texture id="inherit" length_s="1" length_t="2"/>
            <children>
                <componentref id="Cube" />
            </children>
        </component>

        <!-- Plant -->
        <component id="Plant">
            <transformation>
                <translate x="19" y="0" z="19" />
                <scale x="0.5" y="0.5" z="0.5" />
                <rotate axis="z" angle="90" />
            </transformation>
            <materials>
                <material id="moreDiffuse" />
            </materials>
            <texture id="inherit" length_s="1" length_t="2"/>
            <children>
                <componentref id="Earth" />
                <componentref id="VaseCylinder" />
                <componentref id="PlantBody" />
                <componentref id="PlantHead" />
            </children>
        </component>

    

        <component id="Earth">
            <transformation>
                <translate x="2" y="0" z="0" />
                <scale x="1" y="1" z="1" />
                <rotate axis="z" angle="90" />
                <scale x="1" y="0.3" z="1" />
            </transformation>
            <materials>
                <material id="inherit" />
            </materials>
            <texture id="earthTexture" length_s="1" length_t="2"/>
            <children>
                <primitiveref id="demoSphere" />
            </children>
        </component>

        <component id="VaseCylinder">
            <transformation>
                <scale x="0.5" y="0.5" z="0.5" />
                <rotate axis="y" angle="90" />
            </transformation>
            <materials>
                <material id="inherit" />
            </materials>
            <texture id="vaseTexture" length_s="1" length_t="2"/>
            <children>
                <primitiveref id="vase" />
            </children>
        </component>

        <component id="PlantBody">
            <transformation>
                <translate x="2" y="0" z="0" />
                <scale x="0.3" y="0.45" z="0.45" />
                <rotate axis="y" angle="90" />
            </transformation>
            <materials>
                <material id="inherit" />
            </materials>
            <texture id="cactusTexture" length_s="0.25" length_t="0.25"/>
            <children>
                <primitiveref id="demoCylinder" />
            </children>
        </component>

        <component id="PlantHead">
            <transformation>
                <translate x="3" y="0" z="0" />
                <scale x="0.9" y="0.9" z="0.9" />
            </transformation>
            <materials>
                <material id="inherit" />
            </materials>
            <texture id="cactusTexture" length_s="0.25" length_t="0.25"/>
            <children>
                <primitiveref id="demoSphere" />
            </children>
        </component>

        <!-- Basket of fruit -->

        <component id="Basket">
            <transformation>
                <translate x="15" y="3.6" z="6.5" />
            </transformation>
            <materials>
                <material id="moreDiffuse" />
                <material id="demoMaterial" />
            </materials>
            <texture id="steelTexture" length_s="1" length_t="1"/>
            <children>
                <componentref id="baseBasket" />
                <componentref id="holderBasket1" />
                <componentref id="holderBasket2" />
                <componentref id="holderBasket3" />
                <componentref id="holderBasket4" />
                <componentref id="holderBasket5" />
                <componentref id="holderBasket6" />
                <componentref id="holderBasket7" />
                <componentref id="holderBasket8" />
                <componentref id="holderSphere1" />
                <componentref id="holderSphere2" />
                <componentref id="holderSphere3" />
                <componentref id="holderSphere4" />
                <componentref id="holderSphere5" />
                <componentref id="holderSphere6" />
                <componentref id="holderSphere7" />
                <componentref id="holderSphere8" />
            </children>
        </component>

        <component id="baseBasket">
            <transformation>
                <scale x="0.3" y="0.1" z="0.3" />
            </transformation>
            <materials>
                <material id="inherit" />
            </materials>
            <texture id="inherit" length_s="1" length_t="1"/>
            <children>
                <primitiveref id="demoSphere" />
            </children>
        </component>

        <component id="holderBasket1">
            <transformation>
                <translate x="0" y="0" z="0.2" />
                <rotate axis="x" angle="-30" />
                <scale x="0.02" y="0.02" z="0.2" />
            </transformation>
            <materials>
                <material id="inherit" />
            </materials>
            <texture id="inherit" length_s="1" length_t="1"/>
            <children>
                <primitiveref id="demoCylinder" />
            </children>
        </component>

        <component id="holderBasket2">
            <transformation>
                <translate x="0" y="0" z="-0.2" />
                <rotate axis="x" angle="-150" />
                <scale x="0.02" y="0.02" z="0.2" />
            </transformation>
            <materials>
                <material id="inherit" />
            </materials>
            <texture id="inherit" length_s="1" length_t="1"/>
            <children>
                <primitiveref id="demoCylinder" />
            </children>
        </component>

        <component id="holderBasket3">
            <transformation>
                <translate x="0.2" y="0" z="0" />
                <rotate axis="z" angle="30" />
                <rotate axis="y" angle="90" />
                <scale x="0.02" y="0.02" z="0.2" />
            </transformation>
            <materials>
                <material id="inherit" />
            </materials>
            <texture id="inherit" length_s="1" length_t="1"/>
            <children>
                <primitiveref id="demoCylinder" />
            </children>
        </component>
        

        <component id="holderBasket4">
            <transformation>
                <translate x="-0.2" y="0" z="0" />
                <rotate axis="z" angle="120" />
                <rotate axis="z" angle="30" />
                <rotate axis="y" angle="90" />
                <scale x="0.02" y="0.02" z="0.2" />
            </transformation>
            <materials>
                <material id="inherit" />
            </materials>
            <texture id="inherit" length_s="1" length_t="1"/>
            <children>
                <primitiveref id="demoCylinder" />
            </children>
        </component>

        <component id="holderBasket5">
            <transformation>
                <rotate axis="y" angle="45" />
                <translate x="-0.2" y="0" z="0" />
                <rotate axis="z" angle="120" />
                <rotate axis="z" angle="30" />
                <rotate axis="y" angle="90" />
                <scale x="0.02" y="0.02" z="0.2" />
            </transformation>
            <materials>
                <material id="inherit" />
            </materials>
            <texture id="inherit" length_s="1" length_t="1"/>
            <children>
                <primitiveref id="demoCylinder" />
            </children>
        </component>

        <component id="holderBasket6">
            <transformation>
                <rotate axis="y" angle="45" />
                <translate x="0.2" y="0" z="0" />
                <rotate axis="z" angle="30" />
                <rotate axis="y" angle="90" />
                <scale x="0.02" y="0.02" z="0.2" />
            </transformation>
            <materials>
                <material id="inherit" />
            </materials>
            <texture id="inherit" length_s="1" length_t="1"/>
            <children>
                <primitiveref id="demoCylinder" />
            </children>
        </component>

        <component id="holderBasket7">
            <transformation>
                <rotate axis="y" angle="45" />
                <translate x="0" y="0" z="-0.2" />
                <rotate axis="x" angle="-150" />
                <scale x="0.02" y="0.02" z="0.2" />
            </transformation>
            <materials>
                <material id="inherit" />
            </materials>
            <texture id="inherit" length_s="1" length_t="1"/>
            <children>
                <primitiveref id="demoCylinder" />
            </children>
        </component>

        <component id="holderBasket8">
            <transformation>
                <rotate axis="y" angle="45" />
                <translate x="0" y="0" z="0.2" />
                <rotate axis="x" angle="-30" />
                <scale x="0.02" y="0.02" z="0.2" />
            </transformation>
            <materials>
                <material id="inherit" />
            </materials>
            <texture id="inherit" length_s="1" length_t="1"/>
            <children>
                <primitiveref id="demoCylinder" />
            </children>
        </component>

        <component id="holderSphere1">
            <transformation>
                <translate x="0.9" y="0.4" z="0" />
                <scale x="0.1" y="0.1" z="0.1" />
            </transformation>
            <materials>
                <material id="inherit" />
            </materials>
            <texture id="inherit" length_s="1" length_t="1"/>
            <children>
                <primitiveref id="demoSphere" />
            </children>
        </component>

        <component id="holderSphere2">
            <transformation>
                <translate x="-0.9" y="0.4" z="0" />
                <scale x="0.1" y="0.1" z="0.1" />
            </transformation>
            <materials>
                <material id="inherit" />
            </materials>
            <texture id="inherit" length_s="1" length_t="1"/>
            <children>
                <primitiveref id="demoSphere" />
            </children>
        </component>

        <component id="holderSphere3">
            <transformation>
                <translate x="0" y="0.4" z="0.9" />
                <scale x="0.1" y="0.1" z="0.1" />
            </transformation>
            <materials>
                <material id="inherit" />
            </materials>
            <texture id="inherit" length_s="1" length_t="1"/>
            <children>
                <primitiveref id="demoSphere" />
            </children>
        </component>

        <component id="holderSphere4">
            <transformation>
                <translate x="0" y="0.4" z="-0.9" />
                <scale x="0.1" y="0.1" z="0.1" />
            </transformation>
            <materials>
                <material id="inherit" />
            </materials>
            <texture id="inherit" length_s="1" length_t="1"/>
            <children>
                <primitiveref id="demoSphere" />
            </children>
        </component>

        <component id="holderSphere5">
            <transformation>
                <rotate axis="y" angle="45" />
                <translate x="0" y="0.4" z="-0.9" />
                <scale x="0.1" y="0.1" z="0.1" />
            </transformation>
            <materials>
                <material id="inherit" />
            </materials>
            <texture id="inherit" length_s="1" length_t="1"/>
            <children>
                <primitiveref id="demoSphere" />
            </children>
        </component>

        <component id="holderSphere6">
            <transformation>
                <rotate axis="y" angle="45" />
                <translate x="-0.9" y="0.4" z="0" />
                <scale x="0.1" y="0.1" z="0.1" />
            </transformation>
            <materials>
                <material id="inherit" />
            </materials>
            <texture id="inherit" length_s="1" length_t="1"/>
            <children>
                <primitiveref id="demoSphere" />
            </children>
        </component>

        <component id="holderSphere7">
            <transformation>
                <rotate axis="y" angle="45" />
                <translate x="0" y="0.4" z="0.9" />
                <scale x="0.1" y="0.1" z="0.1" />
            </transformation>
            <materials>
                <material id="inherit" />
            </materials>
            <texture id="inherit" length_s="1" length_t="1"/>
            <children>
                <primitiveref id="demoSphere" />
            </children>
        </component>

        <component id="holderSphere8">
            <transformation>
                <rotate axis="y" angle="45" />
                <translate x="0.9" y="0.4" z="0" />
                <scale x="0.1" y="0.1" z="0.1" />
            </transformation>
            <materials>
                <material id="inherit" />
            </materials>
            <texture id="inherit" length_s="1" length_t="1"/>
            <children>
                <primitiveref id="demoSphere" />
            </children>
        </component>

        <!-- Fruit -->

        <component id="Fruit">
            <transformation>
            </transformation>
            <materials>
                <material id="moreDiffuse" />
            </materials>
            <texture id="inherit" length_s="1" length_t="1"/>
            <children>
                <componentref id="Fruit1" />
                <componentref id="Fruit2" />
            </children>
        </component>        
        
        <component id="Fruit1">
            <transformation>
                <translate x="14.8" y="3.8" z="6.5" />
                <scale x="0.2" y="0.2" z="0.2" />
            </transformation>
            <materials>
                <material id="inherit" />
            </materials>
            <texture id="orangeTexture" length_s="1" length_t="1"/>
            <children>
                <primitiveref id="demoSphere" />
            </children>
        </component>

        <component id="Fruit2">
            <transformation>
                <translate x="15.2" y="3.9" z="6.3" />
                <scale x="0.2" y="0.2" z="0.2" />
            </transformation>
            <materials>
                <material id="inherit" />
            </materials>
            <texture id="appleTexture" length_s="1" length_t="1"/>
            <children>
                <primitiveref id="demoSphere" />
            </children>
        </component>

        <!-- Sofa -->
        <component id="Sofa">
            <transformation>
            </transformation>
            <materials>
                <material id="moreDiffuse" />
            </materials>
            <texture id="greenSofaTexture" length_s="1" length_t="1"/>
            <children>
                <componentref id="sofaBody" />
                <componentref id="sofaSide1" />
                <componentref id="sofaSide2" />
                <componentref id="sofaBack" />
                <componentref id="sofaTorus1" />
                <componentref id="sofaTorus2" />
                <componentref id="sofaTorus3" />
                <componentref id="sofaTorus4" />
                <componentref id="sofaTorus5" />
                <componentref id="sofaTorus6" />
                <componentref id="sofaTorus7" />
                <componentref id="sofaTorus8" />
                <componentref id="sofaTorus9" />
                <componentref id="sofaTorus10" />
                <componentref id="sofaTorus11" />
                <componentref id="sofaTorus12" />
                <componentref id="sofaTorus13" />
                <componentref id="sofaTorus14" />
                <componentref id="sofaTorus15" />
                <componentref id="sofaTorus16" />
                <componentref id="sofaTorus17" />
                <componentref id="sofaTorus18" />
                <componentref id="sofaTorus19" />
                <componentref id="sofaTorus20" />
                <componentref id="sofaTorus21" />
                <componentref id="sofaTorus22" />
                <componentref id="sofaTorus23" />
                <componentref id="sofaTorus24" />

            </children>
        </component>

        <component id="sofaBody">
            <transformation>
                <translate x="2" y="0" z="8" />
                <scale x="7" y="2" z="2" />
            </transformation>
            <materials>
                <material id="inherit" />
            </materials>
            <texture id="inherit" length_s="1" length_t="1"/>
            <children>
                <componentref id="Cube" />
            </children>
        </component>

        <component id="sofaSide1">
            <transformation>
                <translate x="1" y="0" z="8" />
                <scale x="1" y="3" z="3" />
            </transformation>
            <materials>
                <material id="inherit" />
            </materials>
            <texture id="inherit" length_s="1" length_t="1"/>
            <children>
                <componentref id="Cube" />
            </children>
        </component>

        <component id="sofaSide2">
            <transformation>
                <translate x="8" y="0" z="8" />
                <scale x="1" y="3" z="3" />
            </transformation>
            <materials>
                <material id="inherit" />
            </materials>
            <texture id="inherit" length_s="1" length_t="1"/>
            <children>
                <componentref id="Cube" />
            </children>
        </component>

        <component id="sofaBack">
            <transformation>
                <translate x="1" y="0" z="10" />
                <scale x="8" y="4" z="1" />
            </transformation>
            <materials>
                <material id="inherit" />
            </materials>
            <texture id="inherit" length_s="1" length_t="1"/>
            <children>
                <componentref id="Cube" />
            </children>
        </component>

        <component id="sofaTorus1">
            <transformation>
                <translate x="1.5" y="3" z="8.2" />
                <scale x="0.3" y="0.3" z="0.3" />
            </transformation>
            <materials>
                <material id="inherit" />
            </materials>
            <texture id="inherit" length_s="1" length_t="1"/>
            <children>
                <primitiveref id="demoTorus" />
            </children>
        </component>

        <component id="sofaTorus2">
            <transformation>
                <translate x="1.5" y="3" z="8.7" />
                <scale x="0.3" y="0.3" z="0.3" />
            </transformation>
            <materials>
                <material id="inherit" />
            </materials>
            <texture id="inherit" length_s="1" length_t="1"/>
            <children>
                <primitiveref id="demoTorus" />
            </children>
        </component>

        <component id="sofaTorus3">
            <transformation>
                <translate x="1.5" y="3" z="9.2" />
                <scale x="0.3" y="0.3" z="0.3" />
            </transformation>
            <materials>
                <material id="inherit" />
            </materials>
            <texture id="inherit" length_s="1" length_t="1"/>
            <children>
                <primitiveref id="demoTorus" />
            </children>
        </component>

        <component id="sofaTorus4">
            <transformation>
                <translate x="1.5" y="3" z="9.7" />
                <scale x="0.3" y="0.3" z="0.3" />
            </transformation>
            <materials>
                <material id="inherit" />
            </materials>
            <texture id="inherit" length_s="1" length_t="1"/>
            <children>
                <primitiveref id="demoTorus" />
            </children>
        </component>

        <component id="sofaTorus5">
            <transformation>
                <translate x="8.5" y="3" z="8.2" />
                <scale x="0.3" y="0.3" z="0.3" />
            </transformation>
            <materials>
                <material id="inherit" />
            </materials>
            <texture id="inherit" length_s="1" length_t="1"/>
            <children>
                <primitiveref id="demoTorus" />
            </children>
        </component>

        <component id="sofaTorus6">
            <transformation>
                <translate x="8.5" y="3" z="8.7" />
                <scale x="0.3" y="0.3" z="0.3" />
            </transformation>
            <materials>
                <material id="inherit" />
            </materials>
            <texture id="inherit" length_s="1" length_t="1"/>
            <children>
                <primitiveref id="demoTorus" />
            </children>
        </component>

        <component id="sofaTorus7">
            <transformation>
                <translate x="8.5" y="3" z="9.2" />
                <scale x="0.3" y="0.3" z="0.3" />
            </transformation>
            <materials>
                <material id="inherit" />
            </materials>
            <texture id="inherit" length_s="1" length_t="1"/>
            <children>
                <primitiveref id="demoTorus" />
            </children>
        </component>

        <component id="sofaTorus8">
            <transformation>
                <translate x="8.5" y="3" z="9.7" />
                <scale x="0.3" y="0.3" z="0.3" />
            </transformation>
            <materials>
                <material id="inherit" />
            </materials>
            <texture id="inherit" length_s="1" length_t="1"/>
            <children>
                <primitiveref id="demoTorus" />
            </children>
        </component>

        <component id="sofaTorus9">
            <transformation>
                <translate x="1.3" y="4" z="10.5" />
                <rotate axis="y" angle="90" />
                <scale x="0.3" y="0.3" z="0.3" />
            </transformation>
            <materials>
                <material id="inherit" />
            </materials>
            <texture id="inherit" length_s="1" length_t="1"/>
            <children>
                <primitiveref id="demoTorus" />
            </children>
        </component>

        <component id="sofaTorus10">
            <transformation>
                <translate x="1.8" y="4" z="10.5" />
                <rotate axis="y" angle="90" />
                <scale x="0.3" y="0.3" z="0.3" />
            </transformation>
            <materials>
                <material id="inherit" />
            </materials>
            <texture id="inherit" length_s="1" length_t="1"/>
            <children>
                <primitiveref id="demoTorus" />
            </children>
        </component>

        <component id="sofaTorus11">
            <transformation>
                <translate x="2.3" y="4" z="10.5" />
                <rotate axis="y" angle="90" />
                <scale x="0.3" y="0.3" z="0.3" />
            </transformation>
            <materials>
                <material id="inherit" />
            </materials>
            <texture id="inherit" length_s="1" length_t="1"/>
            <children>
                <primitiveref id="demoTorus" />
            </children>
        </component>

        <component id="sofaTorus12">
            <transformation>
                <translate x="2.8" y="4" z="10.5" />
                <rotate axis="y" angle="90" />
                <scale x="0.3" y="0.3" z="0.3" />
            </transformation>
            <materials>
                <material id="inherit" />
            </materials>
            <texture id="inherit" length_s="1" length_t="1"/>
            <children>
                <primitiveref id="demoTorus" />
            </children>
        </component>

        <component id="sofaTorus13">
            <transformation>
                <translate x="3.3" y="4" z="10.5" />
                <rotate axis="y" angle="90" />
                <scale x="0.3" y="0.3" z="0.3" />
            </transformation>
            <materials>
                <material id="inherit" />
            </materials>
            <texture id="inherit" length_s="1" length_t="1"/>
            <children>
                <primitiveref id="demoTorus" />
            </children>
        </component>

        <component id="sofaTorus14">
            <transformation>
                <translate x="3.8" y="4" z="10.5" />
                <rotate axis="y" angle="90" />
                <scale x="0.3" y="0.3" z="0.3" />
            </transformation>
            <materials>
                <material id="inherit" />
            </materials>
            <texture id="inherit" length_s="1" length_t="1"/>
            <children>
                <primitiveref id="demoTorus" />
            </children>
        </component>

        <component id="sofaTorus15">
            <transformation>
                <translate x="4.3" y="4" z="10.5" />
                <rotate axis="y" angle="90" />
                <scale x="0.3" y="0.3" z="0.3" />
            </transformation>
            <materials>
                <material id="inherit" />
            </materials>
            <texture id="inherit" length_s="1" length_t="1"/>
            <children>
                <primitiveref id="demoTorus" />
            </children>
        </component>

        <component id="sofaTorus16">
            <transformation>
                <translate x="4.8" y="4" z="10.5" />
                <rotate axis="y" angle="90" />
                <scale x="0.3" y="0.3" z="0.3" />
            </transformation>
            <materials>
                <material id="inherit" />
            </materials>
            <texture id="inherit" length_s="1" length_t="1"/>
            <children>
                <primitiveref id="demoTorus" />
            </children>
        </component>

        <component id="sofaTorus17">
            <transformation>
                <translate x="5.3" y="4" z="10.5" />
                <rotate axis="y" angle="90" />
                <scale x="0.3" y="0.3" z="0.3" />
            </transformation>
            <materials>
                <material id="inherit" />
            </materials>
            <texture id="inherit" length_s="1" length_t="1"/>
            <children>
                <primitiveref id="demoTorus" />
            </children>
        </component>

        <component id="sofaTorus18">
            <transformation>
                <translate x="5.8" y="4" z="10.5" />
                <rotate axis="y" angle="90" />
                <scale x="0.3" y="0.3" z="0.3" />
            </transformation>
            <materials>
                <material id="inherit" />
            </materials>
            <texture id="inherit" length_s="1" length_t="1"/>
            <children>
                <primitiveref id="demoTorus" />
            </children>
        </component>

        <component id="sofaTorus19">
            <transformation>
                <translate x="6.3" y="4" z="10.5" />
                <rotate axis="y" angle="90" />
                <scale x="0.3" y="0.3" z="0.3" />
            </transformation>
            <materials>
                <material id="inherit" />
            </materials>
            <texture id="inherit" length_s="1" length_t="1"/>
            <children>
                <primitiveref id="demoTorus" />
            </children>
        </component>

        <component id="sofaTorus20">
            <transformation>
                <translate x="6.8" y="4" z="10.5" />
                <rotate axis="y" angle="90" />
                <scale x="0.3" y="0.3" z="0.3" />
            </transformation>
            <materials>
                <material id="inherit" />
            </materials>
            <texture id="inherit" length_s="1" length_t="1"/>
            <children>
                <primitiveref id="demoTorus" />
            </children>
        </component>

        <component id="sofaTorus21">
            <transformation>
                <translate x="7.3" y="4" z="10.5" />
                <rotate axis="y" angle="90" />
                <scale x="0.3" y="0.3" z="0.3" />
            </transformation>
            <materials>
                <material id="inherit" />
            </materials>
            <texture id="inherit" length_s="1" length_t="1"/>
            <children>
                <primitiveref id="demoTorus" />
            </children>
        </component>

        <component id="sofaTorus22">
            <transformation>
                <translate x="7.8" y="4" z="10.5" />
                <rotate axis="y" angle="90" />
                <scale x="0.3" y="0.3" z="0.3" />
            </transformation>
            <materials>
                <material id="inherit" />
            </materials>
            <texture id="inherit" length_s="1" length_t="1"/>
            <children>
                <primitiveref id="demoTorus" />
            </children>
        </component>

        <component id="sofaTorus23">
            <transformation>
                <translate x="8.3" y="4" z="10.5" />
                <rotate axis="y" angle="90" />
                <scale x="0.3" y="0.3" z="0.3" />
            </transformation>
            <materials>
                <material id="inherit" />
            </materials>
            <texture id="inherit" length_s="1" length_t="1"/>
            <children>
                <primitiveref id="demoTorus" />
            </children>
        </component>

        <component id="sofaTorus24">
            <transformation>
                <translate x="8.8" y="4" z="10.5" />
                <rotate axis="y" angle="90" />
                <scale x="0.3" y="0.3" z="0.3" />
            </transformation>
            <materials>
                <material id="inherit" />
            </materials>
            <texture id="inherit" length_s="1" length_t="1"/>
            <children>
                <primitiveref id="demoTorus" />
            </children>
        </component>

    </components>



</lxs>